estorch
