Metadata-Version: 2.1
Name: estorch
Version: 1.0.4
Summary: Evolution Strategy Library
Home-page: https://github.com/goktug97/estorch
Author: Göktuğ Karakaşlı
Author-email: karakasligk@gmail.com
License: MIT
Platform: UNKNOWN
Classifier: Programming Language :: Python :: 3
Classifier: License :: OSI Approved :: MIT License
Classifier: Operating System :: OS Independent
Requires-Python: >=3.6
